project_creator/__init__.py
project_creator/config.py
project_creator/main.py
project_creator/utils.py
EZ_project_creator-1.0.4.dist-info/LICENCE
EZ_project_creator-1.0.4.dist-info/METADATA
EZ_project_creator-1.0.4.dist-info/WHEEL
EZ_project_creator-1.0.4.dist-info/entry_points.txt
EZ_project_creator-1.0.4.dist-info/top_level.txt
EZ_project_creator-1.0.4.dist-info/RECORD
