Metadata-Version: 2.1
Name: EZ_project_creator
Version: 1.0.4
Summary: A tool to create project structures with virtual environments and package installations
Home-page: https://github.com/Mark-Friese/project_creator
Author: Mark Friese
Author-email: mark.friese.meng@gmail.com
Classifier: Programming Language :: Python :: 3
Classifier: License :: OSI Approved :: MIT License
Classifier: Operating System :: OS Independent
Requires-Python: >=3.6
License-File: LICENCE
